README.rst
setup.py
timepiece/__init__.py
timepiece/grammar.py
timepiece/helpers.py
timepiece/sizing.py
timepiece/spec.py
timepiece.egg-info/PKG-INFO
timepiece.egg-info/SOURCES.txt
timepiece.egg-info/dependency_links.txt
timepiece.egg-info/requires.txt
timepiece.egg-info/top_level.txt
timepiece/sections/__init__.py
timepiece/sections/base.py
timepiece/sections/final.py
timepiece/sections/sections.py