Metadata-Version: 1.0
Name: timepiece
Version: 0.2.5
Summary: Thin DSL for creating time scheduling specifications
Home-page: http://timepiece.readthedocs.io
Author: Stephen Moore
Author-email: stephen@delfick.com
License: MIT
Keywords: scheduling time specification
Platform: UNKNOWN
